bktree_python/__init__.py
bktree_python/BKTree.py
bktree_python/utils.py
bktree_python-0.6.2.dist-info/LICENSE
bktree_python-0.6.2.dist-info/METADATA
bktree_python-0.6.2.dist-info/WHEEL
bktree_python-0.6.2.dist-info/RECORD
