Metadata-Version: 2.1
Name: bktree-python
Version: 0.6.2
Summary: Python implementation of Burkhard-Keller Trees (BK-Tree)
License: MIT
Author: Armasse
Author-email: armasse35@gmail.com
Requires-Python: >=3.12,<4.0
Classifier: License :: OSI Approved :: MIT License
Classifier: Programming Language :: Python :: 3
Classifier: Programming Language :: Python :: 3.12
